{
  "faturas": [
    {
      "id": 1,
      "numero_fatura": "30662617",
      "data_pagamento": "2020-02-05",
      "referencia": "0000036120200100",
      "competencia": "01/2020",
      "valor_fatura": 100.5
    },
    {
      "id": 2,
      "numero_fatura": "30662617",
      "data_pagamento": "2020-02-05",
      "referencia": "0000036120200100",
      "competencia": "02/2020",
      "valor_fatura": 87.76
    },
    {
      "id": 3,
      "numero_fatura": "30662617",
      "data_pagamento": "2020-02-05",
      "referencia": "0000036120200100",
      "competencia": "03/2020",
      "valor_fatura": 79.54
    },
    {
      "id": 4,
      "numero_fatura": "30662617",
      "data_pagamento": "2020-02-05",
      "referencia": "0000036120200100",
      "competencia": "04/2020",
      "valor_fatura": 102.23
    },
    {
      "id": 5,
      "numero_fatura": "30662617",
      "data_pagamento": "2020-02-05",
      "referencia": "0000036120200100",
      "competencia": "05/2020",
      "valor_fatura": 90.63
    },
    {
      "id": 6,
      "numero_fatura": "30662617",
      "data_pagamento": "2020-02-05",
      "referencia": "0000036120200100",
      "competencia": "06/2020",
      "valor_fatura": 150.17
    }
  ]
}
